aws_cdk_secure_modules-0.1.0.dist-info/licenses/LICENSE
tests/__init__.py
tests/test_secure_s3.py
aws_cdk_secure_modules-0.1.0.dist-info/METADATA
aws_cdk_secure_modules-0.1.0.dist-info/WHEEL
aws_cdk_secure_modules-0.1.0.dist-info/top_level.txt
aws_cdk_secure_modules-0.1.0.dist-info/RECORD
