Metadata-Version: 2.4
Name: aws-cdk-secure-modules
Version: 0.1.0
Requires-Python: >=3.12
License-File: LICENSE
Requires-Dist: aws-cdk-lib
Requires-Dist: constructs
Requires-Dist: pytest
Dynamic: license-file
Dynamic: requires-dist
Dynamic: requires-python
